torch_stoi/__init__.py
torch_stoi/debug.py
torch_stoi/stoi.py
torch_stoi-0.2.3.dist-info/LICENSE
torch_stoi-0.2.3.dist-info/METADATA
torch_stoi-0.2.3.dist-info/WHEEL
torch_stoi-0.2.3.dist-info/top_level.txt
torch_stoi-0.2.3.dist-info/RECORD
