Metadata-Version: 2.1
Name: torch-stoi
Version: 0.2.3
Summary: Computes Short Term Objective Intelligibility in PyTorch
Home-page: https://github.com/mpariente/pytorch_stoi
Author: Manuel Pariente
Author-email: pariente.mnl@gmail.com
License: MIT
Classifier: Development Status :: 4 - Beta
Classifier: Intended Audience :: Science/Research
Classifier: License :: OSI Approved :: MIT License
Classifier: Programming Language :: Python :: 3
License-File: LICENSE
